{
    "homepage": "https://xdown.org/",
    "description": "An ads-free idm/torrent varieta",
    "license": "Freeware",
    "version": "1.0.2.7",
    "url": "https://dl.xdown.org/xdown-1.0.2.7.zip",
    "hash": "acfe5515cc77d9e5c923fbb2d81160a9645890fd54cd1c530a90185995975b11",
    "bin": "XDown.exe",
    "extract_dir": "xdown",
    "shortcuts": [
        [
            "XDown.exe",
            "XDown"
        ]
    ],
    "checkver": "Latest update version number:([\\d.]+)",
    "autoupdate": {
        "url": "https://dl.xdown.org/xdown-$version.zip"
    }
}
